{"type":"FeatureCollection","features":[{"type":"Feature","id":"node/313274269","properties":{"id":"node/313274269"},"geometry":{"type":"Point","coordinates":[77.8992272,12.1331737]}},{"type":"Feature","id":"node/353317573","properties":{"id":"node/353317573"},"geometry":{"type":"Point","coordinates":[78.1589864,12.1347988]}},{"type":"Feature","id":"node/353327285","properties":{"id":"node/353327285"},"geometry":{"type":"Point","coordinates":[78.205895,12.3078191]}},{"type":"Feature","id":"node/7142431093","properties":{"id":"node/7142431093"},"geometry":{"type":"Point","coordinates":[78.3671093,11.9138178]}},{"type":"Feature","id":"node/7142431094","properties":{"id":"node/7142431094"},"geometry":{"type":"Point","coordinates":[78.1181144,12.0574306]}},{"type":"Feature","id":"node/5185525788","properties":{"id":"node/5185525788"},"geometry":{"type":"Point","coordinates":[78.4786186,12.0545748]}},{"type":"Feature","id":"node/4927283883","properties":{"id":"node/4927283883"},"geometry":{"type":"Point","coordinates":[78.0728817,12.3041231]}}]}