{"type":"FeatureCollection","features":[{"type":"Feature","id":"node/245586200","properties":{"id":"node/245586200"},"geometry":{"type":"Point","coordinates":[78.2299964,10.2256894]}},{"type":"Feature","id":"node/245586375","properties":{"id":"node/245586375"},"geometry":{"type":"Point","coordinates":[77.9693256,10.365646]}},{"type":"Feature","id":"node/245586675","properties":{"id":"node/245586675"},"geometry":{"type":"Point","coordinates":[77.9463173,10.5324146]}},{"type":"Feature","id":"node/353280830","properties":{"id":"node/353280830"},"geometry":{"type":"Point","coordinates":[77.107671,10.0656229]}},{"type":"Feature","id":"node/354858935","properties":{"id":"node/354858935"},"geometry":{"type":"Point","coordinates":[77.7492413,10.48766]}},{"type":"Feature","id":"node/577559391","properties":{"id":"node/577559391"},"geometry":{"type":"Point","coordinates":[77.4919719,10.233712]}},{"type":"Feature","id":"node/778229947","properties":{"id":"node/778229947"},"geometry":{"type":"Point","coordinates":[77.5154495,10.4511094]}},{"type":"Feature","id":"node/9130043790","properties":{"id":"node/9130043790"},"geometry":{"type":"Point","coordinates":[77.85285,10.1648333]}},{"type":"Feature","id":"node/7139943400","properties":{"id":"node/7139943400"},"geometry":{"type":"Point","coordinates":[77.8520822,10.2877695]}}]}